<?xml version="1.0" encoding="utf-8"?><toc><breadcrumbs><li><a href="N_ShopTools.htm">Docs</a></li><li><a href="N_ShopTools.htm">Shop<wbr />Tools</a></li><li><a href="T_ShopTools_frmTextView.htm">frm<wbr />Text<wbr />View</a></li><li><a href="Methods_T_ShopTools_frmTextView.htm">Methods</a></li></breadcrumbs><tocItems><li><a id="M_ShopTools_frmTextView_btnCancel_Click" href="M_ShopTools_frmTextView_btnCancel_Click.htm">btn<wbr />Cancel_<wbr />Click</a></li><li><a id="M_ShopTools_frmTextView_btnOK_Click" href="M_ShopTools_frmTextView_btnOK_Click.htm">btn<wbr />OK_<wbr />Click</a></li><li><a id="M_ShopTools_frmTextView_Dispose" href="M_ShopTools_frmTextView_Dispose.htm">Dispose</a></li><li><a id="M_ShopTools_frmTextView_InitializeComponent" href="M_ShopTools_frmTextView_InitializeComponent.htm">Initialize<wbr />Component</a></li></tocItems></toc>