<?xml version="1.0" encoding="utf-8"?><toc><breadcrumbs><li><a href="N_Geometry.htm">Docs</a></li><li><a href="N_Geometry.htm">Geometry</a></li><li><a href="T_Geometry_FMatrix4.htm">FMatrix<wbr />4</a></li><li><a href="Overload_Geometry_FMatrix4__ctor.htm">Constructors</a></li></breadcrumbs><tocItems><li><a id="M_Geometry_FMatrix4__ctor" href="M_Geometry_FMatrix4__ctor.htm">FMatrix<wbr />4</a></li><li><a id="M_Geometry_FMatrix4__ctor_1" href="M_Geometry_FMatrix4__ctor_1.htm">FMatrix<wbr />4(<wbr />Single[,])</a></li></tocItems></toc>