<?xml version="1.0" encoding="utf-8"?><toc><breadcrumbs><li><a href="N_Geometry.htm">Docs</a></li><li><a href="N_Geometry.htm">Geometry</a></li><li><a href="T_Geometry_AxisValueTrackerItem.htm">Axis<wbr />Value<wbr />Tracker<wbr />Item</a></li></breadcrumbs><tocItems><li><a id="M_Geometry_AxisValueTrackerItem__ctor" href="M_Geometry_AxisValueTrackerItem__ctor.htm">Constructor</a></li><li><a id="Properties_T_Geometry_AxisValueTrackerItem" class="has-submenu" href="Properties_T_Geometry_AxisValueTrackerItem.htm"><span data-tocFile="../toc/IDBEA.xml" class="icon toggle" onclick="ToggleExpandCollapse(this); return false;"><i class="fa fa-angle-right"> </i></span>Properties</a><ul class="toc-menu is-hidden"> </ul></li><li><a id="Methods_T_Geometry_AxisValueTrackerItem" href="Methods_T_Geometry_AxisValueTrackerItem.htm">Methods</a></li></tocItems></toc>