<?xml version="1.0" encoding="utf-8"?><toc><breadcrumbs><li><a href="N_Html.htm">Docs</a></li><li><a href="N_Html.htm">Html</a></li><li><a href="T_Html_IntRange.htm">Int<wbr />Range</a></li></breadcrumbs><tocItems><li><a id="Overload_Html_IntRange__ctor" class="has-submenu" href="Overload_Html_IntRange__ctor.htm"><span data-tocFile="../toc/IDAWA.xml" class="icon toggle" onclick="ToggleExpandCollapse(this); return false;"><i class="fa fa-angle-right"> </i></span>Constructors</a><ul class="toc-menu is-hidden"> </ul></li><li><a id="Properties_T_Html_IntRange" class="has-submenu" href="Properties_T_Html_IntRange.htm"><span data-tocFile="../toc/IDBWA.xml" class="icon toggle" onclick="ToggleExpandCollapse(this); return false;"><i class="fa fa-angle-right"> </i></span>Properties</a><ul class="toc-menu is-hidden"> </ul></li><li><a id="Methods_T_Html_IntRange" class="has-submenu" href="Methods_T_Html_IntRange.htm"><span data-tocFile="../toc/IDCWA.xml" class="icon toggle" onclick="ToggleExpandCollapse(this); return false;"><i class="fa fa-angle-right"> </i></span>Methods</a><ul class="toc-menu is-hidden"> </ul></li></tocItems></toc>